LICENSE
instruqt_converter/__init__.py
instruqt_converter/convert.py
instruqt_converter/converters/__init__.py
instruqt_converter/converters/dev.py
instruqt_converter/converters/prod.py
instruqt_converter/converters/utils/__init__.py
instruqt_converter/converters/utils/api.py
instruqt_converter/converters/utils/handler.py
instruqt_converter/core/__init__.py
instruqt_converter/core/config.py
instruqt_converter-0.0.1.dist-info/entry_points.txt
instruqt_converter-0.0.1.dist-info/LICENSE
instruqt_converter-0.0.1.dist-info/WHEEL
instruqt_converter-0.0.1.dist-info/METADATA
instruqt_converter-0.0.1.dist-info/RECORD
