Metadata-Version: 2.1
Name: instruqt-converter
Version: 0.0.1
Summary: Python-based CLI utility to convert Instruqt tracks to and from a temporary state for testing
Home-page: https://github.com/nsthompson/instruqt-converter
License: MIT
Author: Nick Thompson
Author-email: nick@imperial.org
Requires-Python: >=3.9,<4.0.0
Classifier: License :: OSI Approved :: MIT License
Classifier: Programming Language :: Python :: 3
Classifier: Programming Language :: Python :: 3.10
Classifier: Programming Language :: Python :: 3.9
Requires-Dist: PyYAML (>=6.0,<7.0)
Requires-Dist: gql[all] (>=3.4.0,<4.0.0)
Requires-Dist: pydantic (>=1.9.1,<2.0.0)
Requires-Dist: python-frontmatter (>=1.0.0,<2.0.0)
Requires-Dist: rich (>=12.5.1,<13.0.0)
Requires-Dist: rich-click (>=1.5.1,<2.0.0)
